Pyhme/__init__.py
Pyhme-0.1.0.dist-info/METADATA
Pyhme-0.1.0.dist-info/WHEEL
Pyhme-0.1.0.dist-info/top_level.txt
Pyhme-0.1.0.dist-info/RECORD
