Metadata-Version: 2.1
Name: Pyhme
Version: 0.1.0
Summary: Pygame Wrapper!
Author: H1387XD
